[
  {
    "address": "tori1fl48vsnmsdzcv85q5d2q4z5ajdha8yu3h07xz8",
    "balance": {
      "denom": "utori",
      "amount": "179785295061049"
    }
  },
  {
    "address": "tori1kcuty7d5mc0rasw6mpmn4nhk99me55cheldr23",
    "balance": {
      "denom": "utori",
      "amount": "96677146254055"
    }
  },
  {
    "address": "tori1jv65s3grqf6v6jl3dp4t6c9t9rk99cd89tn4j0",
    "balance": {
      "denom": "utori",
      "amount": "91103220295161"
    }
  },
  {
    "address": "tori1at6zkjpxleg8nd8u67542fprzgsev6jh5lfzne",
    "balance": {
      "denom": "utori",
      "amount": "72029926557551"
    }
  },
  {
    "address": "tori1a53udazy8ayufvy0s434pfwjcedzqv345c4vs7",
    "balance": {
      "denom": "utori",
      "amount": "31242342025855"
    }
  },
  {
    "address": "tori1efcnw3j074urqryseyx4weahr2p5at9lhwcaju",
    "balance": {
      "denom": "utori",
      "amount": "26109512163942"
    }
  },
  {
    "address": "tori1zw7guf74ez4mlmsxlt0kcgg9yj6hx94zcg9k6w",
    "balance": {
      "denom": "utori",
      "amount": "18478668662058"
    }
  },
  {
    "address": "tori1zw7guf74ez4mlmsxlt0kcgg9yj6hx94zcg9k6w",
    "balance": {
      "denom": "utori",
      "amount": "18478668662058"
    }
  },
  {
    "address": "tori1tygms3xhhs3yv487phx3dw4a95jn7t7lr0zh5n",
    "balance": {
      "denom": "utori",
      "amount": "9678238951424"
    }
  },
  {
    "address": "tori1jmcglw0kv9k2wyj4h52yg66qtn6r5sxyjlhhs3",
    "balance": {
      "denom": "utori",
      "amount": "7634868920001"
    }
  },
  {
    "address": "tori1g7ryul6kv8wv7p032c3shede4yps74h0qlq0a0",
    "balance": {
      "denom": "utori",
      "amount": "5456362028073"
    }
  },
  {
    "address": "tori1s8qa7466v6pnc7mqhntnzx0kukf3nl52ks9eyl",
    "balance": {
      "denom": "utori",
      "amount": "3273934281960"
    }
  },
  {
    "address": "tori10rp3k6jh8nxmrvdxaf6vwcv6z0ad6p7azkv690",
    "balance": {
      "denom": "utori",
      "amount": "2541057917389"
    }
  },
  {
    "address": "tori1k7u0eu80ydk8p6jaw6cup5ta533mqzjmu3ns09",
    "balance": {
      "denom": "utori",
      "amount": "2420957057212"
    }
  },
  {
    "address": "tori1zyakv8ny9p5esrpv3rgls707rd9anjzla2q7vj",
    "balance": {
      "denom": "utori",
      "amount": "1636966257389"
    }
  },
  {
    "address": "tori1zyakv8ny9p5esrpv3rgls707rd9anjzla2q7vj",
    "balance": {
      "denom": "utori",
      "amount": "1636964936291"
    }
  },
  {
    "address": "tori1xwmdtmhmtx0vsz6vd6yjn6z26rwj6c59cz0vfj",
    "balance": {
      "denom": "utori",
      "amount": "1383259394784"
    }
  },
  {
    "address": "tori16n36a4xryrcaf4vtk9nuqq0lzrs3qkmjxvvuaf",
    "balance": {
      "denom": "utori",
      "amount": "1153168976338"
    }
  },
  {
    "address": "tori1a28lq0usqrma2tn5t7vmdg3jnglh3v3qln4ky0",
    "balance": {
      "denom": "utori",
      "amount": "1153033286620"
    }
  },
  {
    "address": "tori184vpdnt4pzkz70ery009l9ac5p8sel7swjewpz",
    "balance": {
      "denom": "utori",
      "amount": "974001715428"
    }
  },
  {
    "address": "tori1wtvzsrcsq5rpeahn885tk3dlg9qpaufpmddcve",
    "balance": {
      "denom": "utori",
      "amount": "668618765023"
    }
  },
  {
    "address": "tori1cjfnzm779ms28zdlq59ztsc6awhuq65fgk8f03",
    "balance": {
      "denom": "utori",
      "amount": "599999994101"
    }
  },
  {
    "address": "tori1hed63muxwkpxulmz0ru52grqkmzs80kq5ervtp",
    "balance": {
      "denom": "utori",
      "amount": "523234711059"
    }
  },
  {
    "address": "tori1kx2k3mpugtwtajd4zsykx90cn8xawe54yqryfy",
    "balance": {
      "denom": "utori",
      "amount": "471356995791"
    }
  },
  {
    "address": "tori1g5g2apu8z7lkt8tffxthpmtzkvr9t6wk4x2ctr",
    "balance": {
      "denom": "utori",
      "amount": "450000905173"
    }
  },
  {
    "address": "tori10vydz8a5dh58rpgttyvjmckd29pvetanzcgra8",
    "balance": {
      "denom": "utori",
      "amount": "439852970000"
    }
  },
  {
    "address": "tori1wue905yydrxfysqq6ewgpsx0zdsdspn0szuv9f",
    "balance": {
      "denom": "utori",
      "amount": "436520767085"
    }
  },
  {
    "address": "tori12vssh8spx53qzg532xpj22sa7e85ts4x5dm4q9",
    "balance": {
      "denom": "utori",
      "amount": "354483078951"
    }
  },
  {
    "address": "tori18cgtgz6q7ly4suukk744cjep4uxhm5z3artxft",
    "balance": {
      "denom": "utori",
      "amount": "327388970808"
    }
  },
  {
    "address": "tori18vqgaasy24kjfx734rutfclme8pjx4j7ty5n60",
    "balance": {
      "denom": "utori",
      "amount": "316268638574"
    }
  },
  {
    "address": "tori167pynxv8j9unttzqj6uvcj4dfehh3eqr0qm68u",
    "balance": {
      "denom": "utori",
      "amount": "312866410504"
    }
  },
  {
    "address": "tori10ecq77dn5yfyhgv5ce2qh54ehlgzkm9e2ya9dv",
    "balance": {
      "denom": "utori",
      "amount": "312862090029"
    }
  },
  {
    "address": "tori1yjfq497pa2y6lc7qxpmx80v5sv7kgdal30r2ls",
    "balance": {
      "denom": "utori",
      "amount": "303676597470"
    }
  },
  {
    "address": "tori16yt5e09y8musfmdev7tckjwac44fq5cqavdqhp",
    "balance": {
      "denom": "utori",
      "amount": "300000927948"
    }
  },
  {
    "address": "tori1vxfn59qpvxe5cc87xtna8h9nqk2qzz3ngtanyr",
    "balance": {
      "denom": "utori",
      "amount": "253520000000"
    }
  },
  {
    "address": "tori15v7qw0xkmp8ssfmd68xzz27eyah973s7m26v36",
    "balance": {
      "denom": "utori",
      "amount": "248612000000"
    }
  },
  {
    "address": "tori1l3ggmanvvmm3ph66tw04gdpyd0qwm7pkjrjvjr",
    "balance": {
      "denom": "utori",
      "amount": "234984124586"
    }
  },
  {
    "address": "tori1eg6v0rpu2fccvk9yrfemawgsvwm9c4gu75eph4",
    "balance": {
      "denom": "utori",
      "amount": "229700390746"
    }
  },
  {
    "address": "tori1tp2x7uux7nah7utrv2ae03zet3l3ksdfh26wcw",
    "balance": {
      "denom": "utori",
      "amount": "216302984363"
    }
  },
  {
    "address": "tori1vdj6wxngdc5pyc75fa4r7u8glgvj7uhhejlw3x",
    "balance": {
      "denom": "utori",
      "amount": "208808773495"
    }
  },
  {
    "address": "tori1shfq05pu5x8lwm4rng44v7qt888hg78wf4g97x",
    "balance": {
      "denom": "utori",
      "amount": "202455523710"
    }
  },
  {
    "address": "tori1v47dvyflzgatgdul52vgxy6fv8rlgmtw3snrvu",
    "balance": {
      "denom": "utori",
      "amount": "200817223689"
    }
  },
  {
    "address": "tori1vflrsu86gmca2pelep9c6y6x6ar0lksdv75dky",
    "balance": {
      "denom": "utori",
      "amount": "199999997809"
    }
  },
  {
    "address": "tori1nd74es93vzlg73kjptjkjkk3xpzc5tgxs3lstm",
    "balance": {
      "denom": "utori",
      "amount": "193538720000"
    }
  },
  {
    "address": "tori185yv4ka7ymn3f6meq7k3g42nxrgfeykjq5aq4e",
    "balance": {
      "denom": "utori",
      "amount": "177509544052"
    }
  },
  {
    "address": "tori17ek7vacyphp4my4j6mxqyv9hf78gs407g3f4kf",
    "balance": {
      "denom": "utori",
      "amount": "159879556065"
    }
  },
  {
    "address": "tori1rxkw7gt7wm4vxs6gxzpnf8ln8jgtvr20etthqr",
    "balance": {
      "denom": "utori",
      "amount": "155228559994"
    }
  },
  {
    "address": "tori1rxkw7gt7wm4vxs6gxzpnf8ln8jgtvr20etthqr",
    "balance": {
      "denom": "utori",
      "amount": "155228559994"
    }
  },
  {
    "address": "tori12q0tdpyj0r3vgshamq3fqa0mjhteay2rk8sqth",
    "balance": {
      "denom": "utori",
      "amount": "145067019366"
    }
  },
  {
    "address": "tori1843zuxx87tfy0rxlfv4ulgvxqt5kk3jjkgln27",
    "balance": {
      "denom": "utori",
      "amount": "130540015525"
    }
  },
  {
    "address": "tori1jdczv7qljyct8shdypww8ga4mjrcf7lndyfv3a",
    "balance": {
      "denom": "utori",
      "amount": "125536873535"
    }
  },
  {
    "address": "tori12kct4cfuwh7vevec7c4y9slmee949qrjhudy68",
    "balance": {
      "denom": "utori",
      "amount": "125253521490"
    }
  },
  {
    "address": "tori196syl290ec9m26kpfgettv7p87gwn8grhfu8gz",
    "balance": {
      "denom": "utori",
      "amount": "124306000000"
    }
  },
  {
    "address": "tori1apqcn77najwgas75kvqpuurg2u73xfd96k3ffj",
    "balance": {
      "denom": "utori",
      "amount": "124306000000"
    }
  },
  {
    "address": "tori1tpfdhhglxp9j8d07ram20v0ej3r554y3563l5g",
    "balance": {
      "denom": "utori",
      "amount": "121615945493"
    }
  },
  {
    "address": "tori1frzr9rs8tfwgte33rug3xpyas4ckj4wdnvyf37",
    "balance": {
      "denom": "utori",
      "amount": "118954819888"
    }
  },
  {
    "address": "tori1tq8s43l0mp9sv6wl72rfsc924a6ryvjvw6fknc",
    "balance": {
      "denom": "utori",
      "amount": "118000000000"
    }
  },
  {
    "address": "tori1xqsz0ymexddg0uqtcfhcep2wjr8tcc8wmhtsst",
    "balance": {
      "denom": "utori",
      "amount": "114744000000"
    }
  },
  {
    "address": "tori1r5p4cleqmr70l7a3hpyl36xf5wcjm75tzg0q3a",
    "balance": {
      "denom": "utori",
      "amount": "112492511914"
    }
  },
  {
    "address": "tori1nm50zycnm9yf33rv8n6lpks24usxzahk4s7muh",
    "balance": {
      "denom": "utori",
      "amount": "107645481088"
    }
  },
  {
    "address": "tori1fukyy3jse0pykml29cex6ksncds0c3elep4lwc",
    "balance": {
      "denom": "utori",
      "amount": "104315186709"
    }
  },
  {
    "address": "tori18sdews8g2caqfcgq9wx483kvr7t6vcsedcamgz",
    "balance": {
      "denom": "utori",
      "amount": "104309967329"
    }
  },
  {
    "address": "tori1gxw6klntj2ayyss52859seww64yh6y4jl0mmtn",
    "balance": {
      "denom": "utori",
      "amount": "100052767046"
    }
  },
  {
    "address": "tori14l68gzarmtcmuu2e475jwmxyntwye875m379zh",
    "balance": {
      "denom": "utori",
      "amount": "100000914998"
    }
  },
  {
    "address": "tori1h4pj6gcj3sczelgr9lzrjfurtk6qul2h4g798e",
    "balance": {
      "denom": "utori",
      "amount": "100000281365"
    }
  },
  {
    "address": "tori1rpf9hfnsaupy39nk8s378tcn8vhqhk3l4uf8cs",
    "balance": {
      "denom": "utori",
      "amount": "100000146171"
    }
  },
  {
    "address": "tori1rpf9hfnsaupy39nk8s378tcn8vhqhk3l4uf8cs",
    "balance": {
      "denom": "utori",
      "amount": "100000146171"
    }
  },
  {
    "address": "tori1umnav3nxvtemu7ghz5t309c6vqtrct0xxp2j8m",
    "balance": {
      "denom": "utori",
      "amount": "91926882571"
    }
  },
  {
    "address": "tori1vgr9gpcmm0rylkzmrvtdaf54g7yzdhstah9tha",
    "balance": {
      "denom": "utori",
      "amount": "87915990100"
    }
  },
  {
    "address": "tori1ej2es5fjztqjcd4pwa0zyvaevtjd2y5wpxzelw",
    "balance": {
      "denom": "utori",
      "amount": "84938789945"
    }
  },
  {
    "address": "tori1lvyp27wjpy2apda9pzxc7rx7fcn3y576m3qf60",
    "balance": {
      "denom": "utori",
      "amount": "83462218589"
    }
  },
  {
    "address": "tori14gs26vlljsfc96f3s6z63gxkdrat6w6h5katd4",
    "balance": {
      "denom": "utori",
      "amount": "82259808064"
    }
  },
  {
    "address": "tori1uj08cjvyk6546atrvfuzak550rhrvpcuw0r9pr",
    "balance": {
      "denom": "utori",
      "amount": "82200000000"
    }
  },
  {
    "address": "tori1symf474wnypes2d3mecllqk6l26rwz8mwjr3tn",
    "balance": {
      "denom": "utori",
      "amount": "82003498135"
    }
  },
  {
    "address": "tori1znhgcje2np5v34nk7j7t4jes4f8mu6al9t4f6r",
    "balance": {
      "denom": "utori",
      "amount": "81843224347"
    }
  },
  {
    "address": "tori1znhgcje2np5v34nk7j7t4jes4f8mu6al9t4f6r",
    "balance": {
      "denom": "utori",
      "amount": "81843158293"
    }
  },
  {
    "address": "tori1wt3vtjzsmz395lf79fyt8jrcteux38ayy6wm84",
    "balance": {
      "denom": "utori",
      "amount": "81631922080"
    }
  },
  {
    "address": "tori1tjlayqy9s4yz6kzz4wjarsed0pggg0gmu08t3j",
    "balance": {
      "denom": "utori",
      "amount": "78597496504"
    }
  },
  {
    "address": "tori1nra74gcsqy88m9xe5r6jpgyfr6w7zj390ek3w8",
    "balance": {
      "denom": "utori",
      "amount": "78354380254"
    }
  },
  {
    "address": "tori10t4pwpaa8tnkv3tk2c4lxdkwyze82l7axdktjq",
    "balance": {
      "denom": "utori",
      "amount": "77502346431"
    }
  },
  {
    "address": "tori12dgvzxvd339paqvu83vx9wq36j0w3zyxsy3uar",
    "balance": {
      "denom": "utori",
      "amount": "76743666647"
    }
  },
  {
    "address": "tori1zf7xqdnz2fppq2q085nx8975n4w94uc4eqaugh",
    "balance": {
      "denom": "utori",
      "amount": "76387995506"
    }
  },
  {
    "address": "tori1zf7xqdnz2fppq2q085nx8975n4w94uc4eqaugh",
    "balance": {
      "denom": "utori",
      "amount": "76387995506"
    }
  },
  {
    "address": "tori1ttgzvn4lwkqe33drcvjxrefu8j9u5x9qvf22vc",
    "balance": {
      "denom": "utori",
      "amount": "76323471668"
    }
  },
  {
    "address": "tori16xd5ywk80tfmehfvp8jcpwqn68tmfaj4ddnx0e",
    "balance": {
      "denom": "utori",
      "amount": "74979353324"
    }
  },
  {
    "address": "tori1eslm0n3ypkd6f67n6ymf08m2t6kt9cypeed4u0",
    "balance": {
      "denom": "utori",
      "amount": "74262916019"
    }
  },
  {
    "address": "tori1y89cf0d8kdyxwhxv8tpk8wt7uwx5ww6r9gvzzj",
    "balance": {
      "denom": "utori",
      "amount": "72645143631"
    }
  },
  {
    "address": "tori1smla95q87rdj2qekx0knewjumfkhw5rft3r4y8",
    "balance": {
      "denom": "utori",
      "amount": "67352866875"
    }
  },
  {
    "address": "tori18ax5uhftk99z5ulzltlf7uwseqxcu2nepjsthj",
    "balance": {
      "denom": "utori",
      "amount": "66934000000"
    }
  },
  {
    "address": "tori1g0hhhhwwrsh2y687pdxcysawj6xelgyagtmr27",
    "balance": {
      "denom": "utori",
      "amount": "66327597702"
    }
  },
  {
    "address": "tori1dy69x4ls39u5kmmu7tcjye9jnrmh6g6ml48dak",
    "balance": {
      "denom": "utori",
      "amount": "64283889214"
    }
  },
  {
    "address": "tori1mq05ml4zmg4eus96k72re3n06ghuz0txvg5zpd",
    "balance": {
      "denom": "utori",
      "amount": "63759623726"
    }
  },
  {
    "address": "tori1mnem0rhjaxcsghe0xw692xysra63xwwdee2wth9s0rkfwh4dxpaq76qqre",
    "balance": {
      "denom": "utori",
      "amount": "63455821012"
    }
  },
  {
    "address": "tori1jtz7h88hzufhwz4pnwaagv6j7czddcz65fvtq2",
    "balance": {
      "denom": "utori",
      "amount": "59116565657"
    }
  },
  {
    "address": "tori14hj2tavq8fpesdwxxcu44rty3hh90vhujrvcmstl4zr3txmfvw9s3hewys",
    "balance": {
      "denom": "utori",
      "amount": "58709174200"
    }
  },
  {
    "address": "tori1ss9a0rs5m603g8m7f3pwen8g9mpqypg908rs0g4ml2zzqjupx25syne2jn",
    "balance": {
      "denom": "utori",
      "amount": "58050000000"
    }
  },
  {
    "address": "tori132h0a3za2c94zlrlcflg0xlw6npms7e0eauwgt",
    "balance": {
      "denom": "utori",
      "amount": "57372005804"
    }
  },
  {
    "address": "tori1c4a8e6lc9uuaeqmlsw6gyyxpvun5pjagfs7p5h",
    "balance": {
      "denom": "utori",
      "amount": "56408192286"
    }
  },
  {
    "address": "tori1qvcy2gqxrdgnnypgsjcr2xz57lf4cs6ngy5njz",
    "balance": {
      "denom": "utori",
      "amount": "55757540546"
    }
  },
  {
    "address": "tori1qvcy2gqxrdgnnypgsjcr2xz57lf4cs6ngy5njz",
    "balance": {
      "denom": "utori",
      "amount": "55757540546"
    }
  }
]